{
  "tests": [
    {
      "name": "Test1",
      "setup": "sudo -H pip3 install pytest",
      "run": "pytest assignments/03Promedio",
      "input": "",
      "output": "",
      "comparison": "included",
      "timeout": 10,
      "points": 33
    },
    {
      "name": "Test2",
      "setup": "sudo -H pip3 install pytest",
      "run": "pytest assignments/06Peso",
      "input": "",
      "output": "",
      "comparison": "included",
      "timeout": 10,
      "points": 33
    },
    {
      "name": "Test3",
      "setup": "sudo -H pip3 install pytest",
      "run": "pytest assignments/07PendienteLinea",
      "input": "",
      "output": "",
      "comparison": "included",
      "timeout": 10,
      "points": 34
    }
  ]
}